canu/__init__.py
canu/version.py
canu/functions/__init__.py
canu/functions/generate_image.py
canu/functions/retrieve_from_web.py
canu-0.18.0.dist-info/LICENSE
canu-0.18.0.dist-info/METADATA
canu-0.18.0.dist-info/WHEEL
canu-0.18.0.dist-info/top_level.txt
canu-0.18.0.dist-info/RECORD
