Metadata-Version: 2.1
Name: canu
Version: 0.18.0
Summary: An opinionated tool for managing your chatbot projects
Home-page: https://github.com/sbslee/canu
Author: Seung-been "Steven" Lee
Author-email: sbstevenlee@gmail.com
License: MIT
License-File: LICENSE
